front11_multi/__init__.py
front11_multi/front11_multi.py
Front11_multi-0.2.0.dist-info/METADATA
Front11_multi-0.2.0.dist-info/WHEEL
Front11_multi-0.2.0.dist-info/top_level.txt
Front11_multi-0.2.0.dist-info/RECORD
